<?xml version="1.0"?>
<preset version="10">
    <type>sequence</type>
    <comment>Create MOV H264 files per segment with thumbnail</comment>
    <sequence>
        <fileType>NONE</fileType>
        <namePattern></namePattern>
        <composition>&lt;name&gt;</composition>
        <includeVideo>True</includeVideo>
        <exportVideo>True</exportVideo>
        <videoMedia>
            <mediaFileType>movie</mediaFileType>
            <commit>FX</commit>
            <flatten>FlattenTracks</flatten>
            <exportHandles>True</exportHandles>
            <nbHandles>5</nbHandles>
        </videoMedia>
        <includeAudio>True</includeAudio>
        <exportAudio>False</exportAudio>
        <audioMedia>
            <mediaFileType>audio</mediaFileType>
            <commit>Original</commit>
            <flatten>NoChange</flatten>
            <exportHandles>True</exportHandles>
            <nbHandles>5</nbHandles>
        </audioMedia>
    </sequence>
    <movie>
        <fileType>QuickTime</fileType>
        <namePattern>&lt;shot name&gt;</namePattern>
        <yuvHeadroom>0</yuvHeadroom>
        <yuvColourSpace>PCS_709</yuvColourSpace>
        <operationalPattern>None</operationalPattern>
        <companyName>Autodesk</companyName>
        <productName>Flame</productName>
        <versionName>2021</versionName>
    </movie>
    <video>
        <fileType>QuickTime</fileType>
        <codec>33622016</codec>
        <codecProfile>
            <rootPath>/opt/Autodesk/mediaconverter/</rootPath>
            <targetVersion>2021</targetVersion>
            <pathSuffix>/profiles/.33622016/HDTV_720p_8Mbits.cdxprof</pathSuffix>
        </codecProfile>
        <namePattern>&lt;shot name&gt;_&lt;video codec&gt;</namePattern>
        <compressionQuality>50</compressionQuality>
        <transferCharacteristic>2</transferCharacteristic>
        <colorimetricSpecification>4</colorimetricSpecification>
        <includeAlpha>False</includeAlpha>
        <overwriteWithVersions>False</overwriteWithVersions>
        <posterFrame>False</posterFrame>
        <useFrameAsPoster>1</useFrameAsPoster>
        <resize>
            <resizeType>fit</resizeType>
            <resizeFilter>gaussian</resizeFilter>
            <width>1920</width>
            <height>1080</height>
            <bitsPerChannel>8</bitsPerChannel>
            <numChannels>3</numChannels>
            <floatingPoint>False</floatingPoint>
            <bigEndian>True</bigEndian>
            <pixelRatio>1</pixelRatio>
            <scanFormat>P</scanFormat>
        </resize>
    </video>
    <name>
        <framePadding>4</framePadding>
        <startFrame>1</startFrame>
        <frameIndex>2</frameIndex>
    </name>
</preset>